apt_ios_repo/__init__.py
apt_ios_repo/packages.py
apt_ios_repo/sources_list.py
apt_ios_repo/utils.py
apt_ios_repo-0.1.dist-info/LICENSE
apt_ios_repo-0.1.dist-info/METADATA
apt_ios_repo-0.1.dist-info/WHEEL
apt_ios_repo-0.1.dist-info/top_level.txt
apt_ios_repo-0.1.dist-info/RECORD
