Metadata-Version: 2.1
Name: apt-ios-repo
Version: 0.1
Summary: Python library to manage and query APT repositories from iOS Jailbreak community
Home-page: https://github.com/arturgoms/python-apt-ios-repo
Author: Artur Gomes
Author-email: contato@arturgomes.com.br
License: MIT
Platform: UNKNOWN
Requires-Python: >=3.9
License-File: LICENSE
Requires-Dist: requests
